{"Name":"Religious Views: Atheism, Agnosticism & Theism","Subject":"['atheism and agnosticism', 'sociology', 'social science', 'religion and spirituality', 'science', 'alternative religions']","Level":"Elementary School","Description":"Sociology of religion is a large branch of sociology. The different views on deities are studied as part of this topic. In this lesson, we compare and contrast the views of theism, atheism, and agnosticism.","Concepts":"['God', 'Deism', 'Theism', 'Atheism', 'Religion', 'Deity', 'Agnosticism', 'Sociology of religion']","URL":"https://study.com/academy/lesson/religious-views-atheism-agnosticism-theism.html"}