{"Name":"Fundamentals of Biology","Subject":"['biology', 'health and fitness', 'science', 'genetics', 'disease', 'molecular biology', 'medicine']","Level":"High School","Description":"Fundamentals of Biology focuses on the basic principles of biochemistry, molecular biology, genetics, and recombinant DNA. These principles are necessary to understanding the basic mechanisms of life and anchor the biological knowledge that is required to understand many of the challenges in everyday life, from human health and disease to loss of biodiversity and environmental quality.","Concepts":"['DNA', 'Evolution', 'Molecular biology', 'Biology', 'Epidemiology', 'Gene', 'Medicine', 'Genetics']","URL":"https://ocw.mit.edu/courses/biology/7-01sc-fundamentals-of-biology-fall-2011/"}